logquicky/__init__.py
logquicky/logquicky.py
logquicky/progressBar.py
logquicky-0.0.6.dist-info/LICENSE
logquicky-0.0.6.dist-info/METADATA
logquicky-0.0.6.dist-info/WHEEL
logquicky-0.0.6.dist-info/top_level.txt
logquicky-0.0.6.dist-info/RECORD
