Metadata-Version: 2.1
Name: logquicky
Version: 0.0.6
Summary: Nicer python logging in one line
Home-page: https://github.com/ischouten/logquicky
Author: Igor Schouten
Author-email: igor@igorschouten.com
License: GPLv3
Keywords: Logging,Colored output
Platform: UNKNOWN
Classifier: Development Status :: 3 - Alpha
Classifier: Intended Audience :: Developers
Classifier: Topic :: Software Development :: Build Tools
Classifier: License :: OSI Approved :: GNU General Public License v3 (GPLv3)
Classifier: Programming Language :: Python :: 3.6
Classifier: Programming Language :: Python :: 3.7
Classifier: Programming Language :: Python :: 3.8
